autoCompileHardhat/__init__.py
autoCompile_hardhat-0.0.3.dist-info/METADATA
autoCompile_hardhat-0.0.3.dist-info/WHEEL
autoCompile_hardhat-0.0.3.dist-info/entry_points.txt
autoCompile_hardhat-0.0.3.dist-info/top_level.txt
autoCompile_hardhat-0.0.3.dist-info/RECORD
