Metadata-Version: 2.1
Name: autoCompile-hardhat
Version: 0.0.3
Summary: A script for hardhat auto compile.
Home-page: https://baidu.com
Author: th35tr0n9
Author-email: th35tr0n9@gmail.com
License: UNKNOWN
Platform: UNKNOWN
